dagster_notdiamond/__init__.py
dagster_notdiamond/py.typed
dagster_notdiamond/resources.py
dagster_notdiamond-0.1.3.dist-info/METADATA
dagster_notdiamond-0.1.3.dist-info/WHEEL
dagster_notdiamond-0.1.3.dist-info/top_level.txt
dagster_notdiamond-0.1.3.dist-info/RECORD
