Metadata-Version: 2.2
Name: dagster-notdiamond
Version: 0.1.3
Summary: Dagster integration with Not Diamond
Requires-Python: >=3.9
Requires-Dist: dagster>=1.8.0
Requires-Dist: notdiamond
